piper_phonemize_cpp.cpython-310-darwin.so
piper_phonemize-1.1.0.dist-info/LICENSE.md
piper_phonemize-1.1.0.dist-info/RECORD
piper_phonemize-1.1.0.dist-info/WHEEL
piper_phonemize-1.1.0.dist-info/top_level.txt
piper_phonemize-1.1.0.dist-info/METADATA
piper_phonemize/__init__.py
piper_phonemize/espeak-ng-data/hy_dict
piper_phonemize/espeak-ng-data/tr_dict
piper_phonemize/espeak-ng-data/mk_dict
piper_phonemize/espeak-ng-data/or_dict
piper_phonemize/espeak-ng-data/sl_dict
piper_phonemize/espeak-ng-data/qu_dict
piper_phonemize/espeak-ng-data/tk_dict
piper_phonemize/espeak-ng-data/hu_dict
piper_phonemize/espeak-ng-data/piqd_dict
piper_phonemize/espeak-ng-data/pap_dict
piper_phonemize/espeak-ng-data/mr_dict
piper_phonemize/espeak-ng-data/lt_dict
piper_phonemize/espeak-ng-data/is_dict
piper_phonemize/espeak-ng-data/la_dict
piper_phonemize/espeak-ng-data/bn_dict
piper_phonemize/espeak-ng-data/kk_dict
piper_phonemize/espeak-ng-data/nl_dict
piper_phonemize/espeak-ng-data/bpy_dict
piper_phonemize/espeak-ng-data/ms_dict
piper_phonemize/espeak-ng-data/grc_dict
piper_phonemize/espeak-ng-data/jbo_dict
piper_phonemize/espeak-ng-data/ht_dict
piper_phonemize/espeak-ng-data/gd_dict
piper_phonemize/espeak-ng-data/ja_dict
piper_phonemize/espeak-ng-data/sjn_dict
piper_phonemize/espeak-ng-data/de_dict
piper_phonemize/espeak-ng-data/mt_dict
piper_phonemize/espeak-ng-data/om_dict
piper_phonemize/espeak-ng-data/pl_dict
piper_phonemize/espeak-ng-data/ru_dict
piper_phonemize/espeak-ng-data/nci_dict
piper_phonemize/espeak-ng-data/uk_dict
piper_phonemize/espeak-ng-data/mto_dict
piper_phonemize/espeak-ng-data/kl_dict
piper_phonemize/espeak-ng-data/py_dict
piper_phonemize/espeak-ng-data/ky_dict
piper_phonemize/espeak-ng-data/fi_dict
piper_phonemize/espeak-ng-data/ta_dict
piper_phonemize/espeak-ng-data/an_dict
piper_phonemize/espeak-ng-data/qya_dict
piper_phonemize/espeak-ng-data/eo_dict
piper_phonemize/espeak-ng-data/cmn_dict
piper_phonemize/espeak-ng-data/ug_dict
piper_phonemize/espeak-ng-data/ku_dict
piper_phonemize/espeak-ng-data/yue_dict
piper_phonemize/espeak-ng-data/ur_dict
piper_phonemize/espeak-ng-data/shn_dict
